beray/__init__.py
beray/client.py
beray/exceptions.py
beray-0.1.2.dist-info/METADATA
beray-0.1.2.dist-info/WHEEL
beray-0.1.2.dist-info/top_level.txt
beray-0.1.2.dist-info/RECORD
