Metadata-Version: 2.4
Name: beray
Version: 0.1.2
Summary: Add your description here
Requires-Python: >=3.11
Requires-Dist: requests>=2.32.4
